pytracetable/__init__.py
pytracetable/core.py
pytracetable-0.3.0.dist-info/LICENSE
pytracetable-0.3.0.dist-info/METADATA
pytracetable-0.3.0.dist-info/WHEEL
pytracetable-0.3.0.dist-info/top_level.txt
pytracetable-0.3.0.dist-info/RECORD
